LICENSE
MANIFEST.in
README
pyproject.toml
setup.py
quantizeml/__init__.py
quantizeml/cli.py
quantizeml/model_io.py
quantizeml/random.py
quantizeml/version.py
quantizeml.egg-info/PKG-INFO
quantizeml.egg-info/SOURCES.txt
quantizeml.egg-info/dependency_links.txt
quantizeml.egg-info/entry_points.txt
quantizeml.egg-info/requires.txt
quantizeml.egg-info/top_level.txt
quantizeml/analysis/__init__.py
quantizeml/analysis/cli.py
quantizeml/analysis/kernel_distribution.py
quantizeml/analysis/quantization_error_api.py
quantizeml/analysis/quantization_error/__init__.py
quantizeml/analysis/quantization_error/common.py
quantizeml/analysis/quantization_error/keras_quantization_error.py
quantizeml/analysis/quantization_error/onnx_quantization_error.py
quantizeml/analysis/tools/__init__.py
quantizeml/analysis/tools/decorators.py
quantizeml/analysis/tools/extractor.py
quantizeml/analysis/tools/metrics.py
quantizeml/debugging/__init__.py
quantizeml/debugging/assertions.py
quantizeml/layers/__init__.py
quantizeml/layers/activations.py
quantizeml/layers/buffer_temp_conv.py
quantizeml/layers/convolution.py
quantizeml/layers/dense.py
quantizeml/layers/depthwise_convolution.py
quantizeml/layers/dropout.py
quantizeml/layers/extract_token.py
quantizeml/layers/layers_base.py
quantizeml/layers/multi_inbounds.py
quantizeml/layers/observer.py
quantizeml/layers/pleiades.py
quantizeml/layers/pooling.py
quantizeml/layers/quantization_params.py
quantizeml/layers/quantizer_layers.py
quantizeml/layers/recorders.py
quantizeml/layers/rescaling.py
quantizeml/layers/separable_convolution.py
quantizeml/layers/stateful_recurrent.py
quantizeml/layers/quantizers/__init__.py
quantizeml/layers/quantizers/aligned_weight_quantizer.py
quantizeml/layers/quantizers/base_quantizer.py
quantizeml/layers/quantizers/output_quantizer.py
quantizeml/layers/quantizers/weight_quantizer.py
quantizeml/layers/reshaping/__init__.py
quantizeml/layers/reshaping/flatten.py
quantizeml/layers/reshaping/permute.py
quantizeml/layers/reshaping/reshape.py
quantizeml/models/__init__.py
quantizeml/models/calibrate.py
quantizeml/models/quantize.py
quantizeml/models/random.py
quantizeml/models/record.py
quantizeml/models/reset_buffers.py
